{
  "data": {
    "_id": 23000,
    "properties": {
      "birthDate": {
        "name": "birthDate",
        "kind": "scalar",
        "type": "date",
        "nullable": true,
        "getter": false,
        "setter": false,
        "array": false,
        "runtimeType": "Date"
      },
      "gender": {
        "name": "gender",
        "kind": "scalar",
        "enum": true,
        "items": [
          "male",
          "female"
        ],
        "type": "Gender",
        "array": false,
        "runtimeType": "Gender"
      },
      "zipCode": {
        "name": "zipCode",
        "kind": "scalar",
        "getter": false,
        "setter": false,
        "type": "string",
        "array": false,
        "runtimeType": "string"
      },
      "address": {
        "name": "address",
        "kind": "scalar",
        "getter": false,
        "setter": false,
        "type": "string",
        "array": false,
        "runtimeType": "string"
      },
      "number": {
        "name": "number",
        "kind": "scalar",
        "getter": false,
        "setter": false,
        "type": "string",
        "array": false,
        "runtimeType": "string"
      },
      "complement": {
        "name": "complement",
        "kind": "scalar",
        "getter": false,
        "setter": false,
        "type": "string",
        "array": false,
        "runtimeType": "string",
        "optional": true
      },
      "support": {
        "name": "support",
        "kind": "scalar",
        "getter": false,
        "setter": false,
        "type": "string",
        "array": false,
        "runtimeType": "string",
        "optional": true
      },
      "state": {
        "name": "state",
        "kind": "m:1",
        "cascade": [
          "persist"
        ],
        "nullable": true,
        "owner": true,
        "type": "State",
        "array": false,
        "runtimeType": "State",
        "optional": true
      },
      "city": {
        "name": "city",
        "kind": "m:1",
        "cascade": [
          "persist"
        ],
        "nullable": true,
        "owner": true,
        "type": "City",
        "array": false,
        "runtimeType": "City",
        "optional": true
      }
    },
    "primaryKeys": [],
    "filters": {},
    "hooks": {},
    "indexes": [],
    "uniques": [],
    "className": "UserInfo",
    "path": "./src/resources/users/entities/userInfo.entity.ts",
    "name": "UserInfo",
    "abstract": false,
    "internal": true,
    "constructorParams": [],
    "toJsonParams": [],
    "extends": "BaseEntity",
    "useCache": true,
    "collection": "user_info"
  },
  "origin": "./src/resources/users/entities/userInfo.entity.ts",
  "hash": "1fb4fa755bd56b3bd65bea66e7327876",
  "version": "6.2.9"
}
